python_rocketchat_sender/__init__.py
python_rocketchat_sender/sender.py
python_rocketchat_sender-0.4.dist-info/LICENSE
python_rocketchat_sender-0.4.dist-info/METADATA
python_rocketchat_sender-0.4.dist-info/WHEEL
python_rocketchat_sender-0.4.dist-info/top_level.txt
python_rocketchat_sender-0.4.dist-info/RECORD
