Metadata-Version: 2.1
Name: python_rocketchat_sender
Version: 0.4
Summary: Send Rocket Chat messages to your server
Home-page: https://github.com/hybridgeeducation/python-rocketchat-sender
Author: Gerardo Mathus
Author-email: gerardo@nextia.mx
Classifier: Programming Language :: Python :: 3
Classifier: License :: OSI Approved :: MIT License
Classifier: Operating System :: OS Independent
Requires-Python: >=3.10
License-File: LICENSE
Requires-Dist: requests
